langchain_s3_text_loaders/__init__.py
langchain_s3_text_loaders/document_loaders/__init__.py
langchain_s3_text_loaders/document_loaders/s3_text_directory_loader.py
langchain_s3_text_loaders/document_loaders/s3_text_file_loader.py
langchain_s3_text_loaders-0.8.3.dist-info/METADATA
langchain_s3_text_loaders-0.8.3.dist-info/WHEEL
langchain_s3_text_loaders-0.8.3.dist-info/top_level.txt
langchain_s3_text_loaders-0.8.3.dist-info/RECORD
