Metadata-Version: 2.1
Name: langchain-s3-text-loaders
Version: 0.8.3
Summary: s3 loaders for simple text files
Author-email: Carmine DiMascio <cdimascio@gmail.com>
License: MIT
Requires-Python: >=3.11
Requires-Dist: botocore
Requires-Dist: langchain-core
Requires-Dist: langchain-community
Requires-Dist: boto3
